multipass/__init__.py
multipass/test_multipass.py
shopify_multipass_login-2.0.0.dist-info/LICENSE
shopify_multipass_login-2.0.0.dist-info/METADATA
shopify_multipass_login-2.0.0.dist-info/WHEEL
shopify_multipass_login-2.0.0.dist-info/top_level.txt
shopify_multipass_login-2.0.0.dist-info/RECORD
